layman/__main__.py
layman/config.py
layman/config.toml
layman/layman.py
layman/utils.py
layman/managers/AutotilingLayoutManager.py
layman/managers/GridLayoutManager.py
layman/managers/MasterStackLayoutManager.py
layman/managers/WorkspaceLayoutManager.py
layman-0.1.0.dist-info/LICENSE
layman-0.1.0.dist-info/METADATA
layman-0.1.0.dist-info/WHEEL
layman-0.1.0.dist-info/entry_points.txt
layman-0.1.0.dist-info/top_level.txt
layman-0.1.0.dist-info/RECORD
