Metadata-Version: 2.1
Name: layman
Version: 0.1.0
Summary: A daemon that handles sway/i3 layout management on a per-workspace basis
License: GPL v3
License-File: LICENSE
Requires-Dist: i3ipc
Requires-Dist: setproctitle
Requires-Dist: tomli
